Workbook

Sheet Bug Tracker
A1: Bug ID | B1: Date Reported | C1: Reported By | D1: App Area | E1: Module | F1: Bug Summary | G1: Steps to Reproduce | H1: Expected Result | I1: Actual Result | J1: Severity | K1: Priority | L1: Status | M1: Assigned To | N1: Target Fix Date | O1: Date Fixed | P1: Retest Date | Q1: Retest Result | R1: Root Cause | S1: Fix Notes | T1: Related Test Case ID | U1: Evidence Link | V1: Comments | W1: Age (Days)
A2: BUG-001 | B2: 46180 | C2: UAT Tester | D2: Customer App | E2: Vehicle Management | F2: The same vehicle can be registered multiple times | G2: Log in, go to the garge and register a vehicle. register the same vehicle a second time | H2: The same vehicle should not be registered multiple times | I2: Duplicate registeration of a vehicle is suceessful | J2: Major | K2: High | L2: New | N2: 46185 | T2: VEH-05
A3: BUG-002 | B3: 46180 | C3: UAT Tester | D3: Customer App | E3: Booking | F3: Booking time slot does not captures all timeslot including the seasonal ones | G3: Open booking and enter all the required fields, on the booking time field select one of the various time slots that is most sutable | H3: Time slot selected | I3: The available time slots does not cover all the time slots that a customer can pick | J3: Critical | K3: Critical | L3: New | N3: 46185 | S3: Use the Seasional sessions table for details of timeslots | T3: ADM-VEN-01
A4: BUG-003 | B4: 46181 | C4: UAT Tester | D4: Customer App | E4: Booking | F4: No service phone no field | G4: Open booking and while entering the required details for the booking, there is no phone no captured for the booking | H4: Service phone no shoud be captured | I4: No field to enter Phone no | J4: Critical | K4: Critical | L4: New | N4: 46185 | T4: BOOK-01
A5: BUG-004 | B5: 46181 | C5: UAT Tester | D5: Customer App | E5: Cancellation | F5: Cancellation policy document not included | G5: Open bookings to view list of bookings, select the booking to cancel and click on cnacel | H5: Cancellation pop up should show with a link to the full cancellation policy | I5: Cancellation pop up shows, but there is no link to cancellation policy | J5: Major | K5: High | L5: New | N5: 46185 | S5: Cancellation policy doc will be provided | T5: CAN-01
A6: BUG-005 | B6: 46181 | C6: UAT Tester | D6: Customer App | E6: Booking | F6: Service address field cannot be verified | G6: Open booking and enter all the required fields, on theservice address field enter any address arbitary value | H6: Service address provided should be a UK(Aberdeen, Scotland precisely) address | I6: User can enter any value and the system accepts it | J6: Critical | K6: High | L6: New | N6: 46185 | S6: Use the Postcode Address Lookup API for address verification. Doc will be provided | T6: BOOK-01
A7: BUG-006 | B7: 46181 | C7: UAT Tester | D7: Customer App | E7: Error Handling | F7: Session does not timeout after hours away | G7: Log in to app and leave app for more than 10 min | H7: Session shoukd timeout sfter begin away from app after some time | I7: Session remains active even after hours of inactivity | J7: Critical | K7: Critical | L7: New | N7: 46185 | T7: ERR-CUS-12
A8: BUG-007 | B8: 46181 | C8: UAT Tester | D8: Customer App | E8: Error Handling | F8: Sign in page does not allow user toggle password on and off | G8: Go to login page and enter email and password. The user cannot view the password he/she is entering | H8: User should be able to toggle on or off the password field to view password being enteed | I8: User cannot see the password being entered | J8: Minor | K8: Medium | L8: New | N8: 46185 | T8: ERR-CUS-01 | W8: =IF(B8="","",TODAY()-B8) -> 7
A9: BUG-008 | B9: 46181 | C9: UAT Tester | D9: Customer App | E9: Error Handling | F9: Error message during network failure | W9: =IF(B9="","",TODAY()-B9) -> 7
A10: BUG-009 | B10: 46185 | C10: UAT Tester | D10: Both | E10: Promotions | F10: Discrepancy with the discount calculations | G10: Created a 10% discount promotion for first time sign-ups in the Admin app and applied to all users. In the user app book a wash, at review booking you would notice a miscalulation to total | H10: 10% discount on the mini-valet service(only) should bring the total to the mini-valet cost -10% | I10: A total of more that 10% was deducted from the mini-valet service(Total for standard wash should have been 22.5 but i got 19.85) | J10: Critical | K10: Critical | L10: New | N10: 46190 | T10: PRO-CUS-03 | W10: =IF(B10="","",TODAY()-B10) -> 3
A11: BUG-010 | B11: 46188 | C11: UAT Tester | D11: Admin App | E11: Dashboard | F11: Total Renenue does not compute | G11: Book a wash on the customer app. Log in to admin app, on the dashboard, the tota revenue does not compute | H11: Total revenue after all bookings should be visible on the dash board | I11: Totla revenue remains at 0.00 | J11: Critical | K11: Critical | L11: New | N11: 46193 | W11: =IF(B11="","",TODAY()-B11) -> 0
A12: BUG-011 | B12: 46188 | C12: UAT Tester | D12: Admin App | E12: Admin Authentication | F12: Admin user session foes not expire after extended periods | G12: Log in to the admin portal and leave the account logged in for extended periods | H12: Admin user should be logged out after a specified period | I12: User remains logged in even after 24 hours | J12: Major | K12: High | L12: New | N12: 46193 | T12: ADM-AUTH-04 | W12: =IF(B12="","",TODAY()-B12) -> 0
W13: =IF(B13="","",TODAY()-B13)
W14: =IF(B14="","",TODAY()-B14)
W15: =IF(B15="","",TODAY()-B15)
W16: =IF(B16="","",TODAY()-B16)
W17: =IF(B17="","",TODAY()-B17)
W18: =IF(B18="","",TODAY()-B18)
W19: =IF(B19="","",TODAY()-B19)
W20: =IF(B20="","",TODAY()-B20)
W21: =IF(B21="","",TODAY()-B21)
W22: =IF(B22="","",TODAY()-B22)
W23: =IF(B23="","",TODAY()-B23)
W24: =IF(B24="","",TODAY()-B24)
... W200: =IF(B200="","",TODAY()-B200)

Sheet Dashboard
A1: NEXA UAT Bug Tracker Dashboard
A3: Metric | B3: Value | C3: Notes
A4: Total Bugs | B4: =COUNTA('Bug Tracker'!$A$2:$A$200) -> 11 | C4: All logged bugs
A5: Open Bugs | B5: =COUNTIFS('Bug Tracker'!$L$2:$L$200,"<>Closed",'Bug Tracker'!$L$2:$L$200,"<>Fixed",'Bug Tracker'!$A$2:$A$200,"<>") -> 11 | C5: Anything not fixed/closed
A6: Fixed Bugs | B6: =COUNTIF('Bug Tracker'!$L$2:$L$200,"Fixed") -> 0 | C6: Ready for closure or release note
A7: Closed Bugs | B7: =COUNTIF('Bug Tracker'!$L$2:$L$200,"Closed") -> 0 | C7: Verified and closed
A8: Critical / High Priority | B8: =COUNTIF('Bug Tracker'!$K$2:$K$200,"Critical") + COUNTIF('Bug Tracker'!$K$2:$K$200,"High") -> 9 | C8: Needs urgent action
A9: Overdue Open Bugs | B9: =COUNTIFS('Bug Tracker'!$N$2:$N$200,"<"&TODAY(),'Bug Tracker'!$L$2:$L$200,"<>Closed",'Bug Tracker'!$L$2:$L$200,"<>Fixed",'Bug Tracker'!$A$2:$A$200,"<>") -> 7 | C9: Target fix date has passed
A12: Status | B12: Count | D12: Priority | E12: Count | G12: App Area | H12: Count
A13: New | B13: =COUNTIF('Bug Tracker'!$L$2:$L$200,A13) -> 10 | D13: Critical | E13: =COUNTIF('Bug Tracker'!$K$2:$K$200,D13) -> 5 | G13: Customer App | H13: =COUNTIF('Bug Tracker'!$D$2:$D$200,G13) -> 8
A14: Triaged | B14: =COUNTIF('Bug Tracker'!$L$2:$L$200,A14) -> 0 | D14: High | E14: =COUNTIF('Bug Tracker'!$K$2:$K$200,D14) -> 4 | G14: Admin App | H14: =COUNTIF('Bug Tracker'!$D$2:$D$200,G14) -> 2
A15: In Progress | B15: =COUNTIF('Bug Tracker'!$L$2:$L$200,A15) -> 0 | D15: Medium | E15: =COUNTIF('Bug Tracker'!$K$2:$K$200,D15) -> 1 | G15: Both | H15: =COUNTIF('Bug Tracker'!$D$2:$D$200,G15) -> 1
A16: Ready for Retest | B16: =COUNTIF('Bug Tracker'!$L$2:$L$200,A16) -> 0 | D16: Low | E16: =COUNTIF('Bug Tracker'!$K$2:$K$200,D16) -> 0
A17: Retesting | B17: =COUNTIF('Bug Tracker'!$L$2:$L$200,A17) -> 0
A18: Fixed | B18: =COUNTIF('Bug Tracker'!$L$2:$L$200,A18) -> 0
A19: Closed | B19: =COUNTIF('Bug Tracker'!$L$2:$L$200,A19) -> 0
A20: Rejected | B20: =COUNTIF('Bug Tracker'!$L$2:$L$200,A20) -> 0
A21: Duplicate | B21: =COUNTIF('Bug Tracker'!$L$2:$L$200,A21) -> 0

Sheet Lists
A1: Status | B1: Priority | C1: Severity | D1: App Area | E1: Module | F1: Environment
A2: New | B2: Critical | C2: Blocker | D2: Customer App | E2: Authentication | F2: UAT
A3: Triaged | B3: High | C3: Critical | D3: Customer App | E3: Vehicle Management | F3: Staging
A4: In Progress | B4: Medium | C4: Major | D4: Customer App | E4: Booking | F4: Production
A5: Ready for Retest | B5: Low | C5: Minor | D5: Customer App | E5: Payment | F5: Development
A6: Retesting | C6: Cosmetic | D6: Customer App | E6: Cancellation
A7: Fixed | D7: Customer App | E7: Review
A8: Closed | D8: Admin App | E8: Admin Authentication
A9: Rejected | D9: Admin App | E9: Booking Management
A10: Duplicate | D10: Admin App | E10: Vendor Assignment
D11: Admin App | E11: Payment & Refund
D12: Admin App | E12: Error Handling
D13: Both | E13: Notifications
D14: Both | E14: Security / Access Control
E15: Promotions
E16: Dashboard

Sheet How to Use
A1: How to Use the NEXA UAT Bug Tracker
A3: Step | B3: Instruction
A4: 1 | B4: Log every defect on the Bug Tracker sheet using one row per bug.
A5: 2 | B5: Use the Bug ID format BUG-001, BUG-002, etc.
A6: 3 | B6: Set Severity based on user/business impact and Priority based on fix urgency.
A7: 4 | B7: Update Status as the bug moves from New → Triaged → In Progress → Ready for Retest → Fixed → Closed.
A8: 5 | B8: Add the related UAT test case ID, such as AUTH-01 or ADM-PAY-04, for traceability.
A9: 6 | B9: Use Evidence Link for screenshots, screen recordings, logs, or ticket links.
A10: 7 | B10: Dashboard updates automatically from the Bug Tracker sheet.
